[
null,
{"id":1,"expanded":true,"name":"MAP001","order":1,"parentId":0,"scrollX":1576.5,"scrollY":636.5},
{"id":2,"expanded":true,"name":"大堂","order":4,"parentId":0,"scrollX":1568.5,"scrollY":805},
{"id":3,"expanded":true,"name":"雪中要塞","order":2,"parentId":0,"scrollX":1568.5,"scrollY":961},
{"id":4,"expanded":false,"name":"教堂","order":5,"parentId":0,"scrollX":1568.5,"scrollY":635},
{"id":5,"expanded":false,"name":"防具商店","order":3,"parentId":0,"scrollX":1568.5,"scrollY":635},
{"id":6,"expanded":false,"name":"MAP006","order":7,"parentId":0,"scrollX":1568.5,"scrollY":635},
{"id":7,"expanded":false,"name":"世界地图 1","order":6,"parentId":0,"scrollX":1576.5,"scrollY":949},
{"id":8,"expanded":false,"name":"村01-1","order":10,"parentId":9,"scrollX":0,"scrollY":0,"quick":false},
{"id":9,"expanded":true,"name":"测试地图 ","order":8,"parentId":0,"scrollX":1568.5,"scrollY":635.5,"quick":false},
{"id":10,"expanded":false,"name":"村01-2","order":11,"parentId":9,"scrollX":1568.5,"scrollY":635,"quick":false},
{"id":11,"expanded":false,"name":"村01-3","order":12,"parentId":9,"scrollX":0,"scrollY":0,"quick":false},
{"id":12,"expanded":false,"name":"村01-4","order":13,"parentId":9,"scrollX":0,"scrollY":0,"quick":false},
{"id":13,"expanded":false,"name":"First","order":9,"parentId":9,"scrollX":1576.5,"scrollY":653.5,"quick":false}
]